<?xml version="1.0" encoding="utf-8" ?>
<!-- eng -->
<Resource xmlns="urn:ComolTranslation">
	<item name="LTpageTitle_t.text">TicketSystem category list</item>
	<item name="LTtitle_t.text">TicketSystem category list</item>
	
	<item name="LTnoData_t.text">No category found</item>
	
	<item name="LNBtable.text">Table</item>
	<item name="LNBtable.ToolTip">Table</item>
	<item name="LNBtable.status">Table</item>

	<item name="LNBtree.text">Tree</item>
	<item name="LNBtree.ToolTip">Tree</item>
	<item name="LNBtree.status">Tree</item>

	<item name="LNBuser.text">Users</item>
	<item name="LNBuser.ToolTip">Users</item>
	<item name="LNBuser.status">Users</item>

	<item name="LBmain_t.text">Drag to reorder categories.</item>  <!-- UPDATE! -->
	
	<item name="LBmain_t.ToolTip">Drag to reorder categories.</item>


	<item name="LNBsave.text" >Save</item>
	<item name="LNBsave.ToolTip">Save</item>
	<item name="LNBsave.status">Save</item>
	
	<item name="LNBsave.ConfirmText">Changes will be saved, do you want to continue?</item>
	
	<item name="Message.Saved">Changes successfully saved.</item>
	<item name="Message.Unsaved">Internal error: changes not saved.</item>
	<item name="Message.NoModified">No changes applied.</item>
	<item name="Message.NoCategories">No category present</item>

	<!-- Add-On -->
	<item name="Error.NoAccess">Category management is temporarily disabled.</item>
	<item name="Error.NoPermission">You do not have permission to access the service.</item>

	<!--Legend-->
	<item name="LTleged_t.text">Legend:</item>
	<item name="Legend.default.Text">Default</item>
	<item name="Legend.default.Title">Default Category</item>
	<item name="Legend.deleted.Text">Deleted</item>
	<item name="Legend.deleted.Title">Category deleted</item>

	<item name="Message.DefaultOrder">CAUTION. The default category can not be reordered or set as a daughter of other categories.</item>

	<!-- Add 10/12/2014 -->
	<item name="HYPtable.text">Table</item>
	<item name="HYPtable.ToolTip">View in tabular form (management)</item>
	<item name="HYPtable.status">View in tabular form (management)</item>

	<item name="HYPtree.text">Tree</item>
	<item name="HYPtree.ToolTip">View Tree (Reorder)</item>
	<item name="HYPtree.status">View Tree (Reorder)</item>

	<item name="HYPuser.text">Users</item>
	<item name="HYPuser.ToolTip">View by users</item>
	<item name="HYPuser.status">View by users</item>

	<!-- Add 25/05/2015 -->

	<item name="Message.UnSended">Notifications blocked: messages will not be sent.</item>
	<item name="Message.Sended">Messages will be sent soon.</item>
	
	<item name="LNBnotifyAll.text">Notify ALL</item>
	<item name="LNBnotifyAll.ToolTip">Send a summary with all the categories to all the managers and resolvers registered in the current community.</item>
	<item name="LNBnotifyAll.status">ISend a summary with all the categories to all the managers and resolvers registered in the current community.</item>

	<item name="LNBnotifyManager.text">Notify Managers</item>
	<item name="LNBnotifyManager.ToolTip">Send a summary with all categories only to managers in the current community.</item>
	<item name="LNBnotifyManager.status">Send a summary with all categories only to managers in the current community.</item>

	<item name="LNBnotifyResolver.text">Notify Resolvers</item>
	<item name="LNBnotifyResolver.ToolTip">Send a summary with all categories only to resolvers in the current community.</item>
	<item name="LNBnotifyResolver.status">Send a summary with all categories only to resolvers in the current community.</item>
</Resource>