<?xml version="1.0" encoding="utf-8" ?>
<Resource xmlns="urn:ComolTranslation">
    <item name="LNBCartellaPrincipale.text">Cartella Principale</item>
    <item name="LNBGestioneDomande.text" disambiguation="domande=domande di un questionario">Gestione Domande</item>
    <item name="LNBSalva.text">Salva Modifiche</item>
    <item name="LBTitolo.text">Selezionare il tipo di domanda:</item>
    <item name="LBerrore.text">Non hai i permessi</item>
    <item name="ErroreOpzioni">Salvataggio della domanda non riuscito, aggiungere almeno un'opzione di risposta</item>
    <item name="ErroreTestoDomanda">Salvataggio della domanda non riuscito, inserire il testo della domanda</item>
    <item name="1.MNUTipoDomanda">RATING </item>
    <item name="2.MNUTipoDomanda">NUMERICA </item>
    <item name="3.MNUTipoDomanda">SCELTA MULTIPLA</item>
    <item name="4.MNUTipoDomanda">DROPDOWN </item>
    <item name="5.MNUTipoDomanda">TESTO LIBERO </item>
    <item name="10.MNUTipoDomanda">RATING STARS </item>
    <item name="LibreriaDiDomande" disambiguation="libreria=libreria di domande">Librerie</item>
    <item name="Modello" disambiguation="modello=modello di questionario">Modelli</item>
    <item name="Autovalutazione">Test di autovalutazione</item>
    <item name="Sondaggio">Sondaggi</item>
    <item name="Questionari">Questionari</item>
    <item name="Meeting">Meeting</item>
</Resource>