<?xml version="1.0" encoding="utf-8"?>
<Resource xmlns:xsi="http://www.w3.org/2001/XMLSchema-instance" xmlns:xsd="http://www.w3.org/2001/XMLSchema" xmlns="urn:ComolTranslation">
  <item name="LBtitolo.text" disambiguation="materiale=file" html="false" placeholder="false">Community-Material</item>
  <item name="LBtitolo.normale" disambiguation="materiale=file" html="false" placeholder="false">Community-Materialverwaltung </item>
  <item name="LBtitolo.dettagli.True" disambiguation="materiale=file" html="false" placeholder="false">Community-Material-Verwaltung: Details des Materials</item>
  <item name="LBtitolo.dettagli.False" disambiguation="materiale=file" html="false" placeholder="false">Community-Material-Verwaltung: Details der Mappe</item>
  <item name="LBtitolo.modifica.True" disambiguation="materiale=file" html="false" placeholder="false">Community-Material-Verwaltung: Änderung des Materials</item>
  <item name="LBtitolo.modifica.False" disambiguation="materiale=file" html="false" placeholder="false">Community-Material-Verwaltung: Änderung der Mappe</item>
  <item name="LBtitolo.upload.True" disambiguation="materiale=file" html="false" placeholder="false">Community-Material-Verwaltung: Material-Upload </item>
  <item name="LBtitolo.upload.False" disambiguation="materiale=file" html="false" placeholder="false">Community-Material-Verwaltung: Erstellung der Mappe</item>
  <item name="LBtitolo.sposta.True" disambiguation="materiale=file" html="false" placeholder="false">Community-Material-Verwaltung: Verschieben Sie das Material</item>
  <item name="LBtitolo.sposta.False" disambiguation="materiale=file" html="false" placeholder="false">Community-Material-Verwaltung: Verschieben Sie die Mappe</item>
  <item name="LBtitolo.dettagliDownload.True" disambiguation="materiale=file" html="false" placeholder="false">Community-Material: Details</item>
  <item name="LBtitolo.dettagliDownload.False" disambiguation="materiale=file" html="false" placeholder="false">Community-Material: Details der Mappe</item>
  <item name="LBNopermessi.text" html="false" placeholder="false">Sie sind nicht berechtigt, auf diese Seite zuzugreifen.</item>
  <item name="LogoutMessage" html="false" placeholder="false">Leider ist die Session abgelaufen. Sie müssen auf das System wieder zugreifen.</item>
  <item name="LNBbackToFileList.text" html="false" placeholder="false">Kehren Sie zum Download zurück</item>
  <item name="LNBbackToFileList.status" html="false" placeholder="false">Kehren Sie zum Download zurück</item>
  <item name="LNBbackToFileList.ToolTip" html="false" placeholder="false">Kehren Sie zum Download zurück</item>
  <item name="LKBaltro.status" html="false" placeholder="false">Andere Zeichen</item>
  <item name="LKBaltro.text" disambiguation="Relativo a caratteri" html="false" placeholder="false">Andere</item>
  <item name="LKBaltro.ToolTip" html="false" placeholder="false">Andere Zeichen</item>
  <item name="LKBtutti.status" disambiguation="Relativo a caratteri" html="false" placeholder="false">Alle</item>
  <item name="LKBtutti.text" disambiguation="Relativo a caratteri" html="false" placeholder="false">Alle</item>
  <item name="LKBtutti.ToolTip" disambiguation="Relativo a caratteri" html="false" placeholder="false">Alle</item>
  <item name="LKBUpload.status" html="false" placeholder="false">Laden Sie hier eine neue Datei</item>
  <item name="LKBUpload.text" html="false" placeholder="false">Upload</item>
  <item name="LKBUpload.ToolTip" html="false" placeholder="false">Laden Sie eine Datei in diese Mappe</item>
  <item name="Lettera.status" disambiguation="lettera=carattere" html="false" placeholder="true" mustcontains="#%%#">Buchstabe #%%#</item>
  <item name="Lettera.ToolTip" disambiguation="lettera=carattere" html="false" placeholder="true" mustcontains="#%%#">Buchstabe #%%#</item>
  <item name="LBnumeroRecord_c.text" html="false" placeholder="false">Anz. Sätze:</item>
  <item name="DGFileDisponibile.page" html="false" placeholder="true" mustcontains="#%%#">Seite &lt;#%%#&gt;</item>
  <item name="DGFileDisponibile.ordinamento.0.status" html="false" placeholder="true" mustcontains="#%%#">Sortierung aufsteigend nach &lt;#%%#&gt;</item>
  <item name="DGFileDisponibile.ordinamento.1.status" html="false" placeholder="true" mustcontains="#%%#">Sortierung absteigend nach &lt;#%%#&gt;</item>
  <item name="DGFileDisponibile.ordinamento.2.status" html="false" placeholder="true" mustcontains="#%%#">Sortieren Sie nach &lt;#%%#&gt;</item>
  <item name="LBnoFile.text" html="false" placeholder="false">Keine Datei nach den angegebenen Parametern identifiziert</item>
  <item name="LNBapriFiltro.text" html="true" placeholder="false">&lt;img src='./../images/filtro_open.gif' alt='' align=middle&gt;Blenden Sie den Filter ein</item>
  <item name="LNBapriFiltro.status" html="false" placeholder="false">Zeigen Sie den Community-Filter an</item>
  <item name="LNBapriFiltro.Tooltip" html="false" placeholder="false">Zeigen Sie den Community-Filter an</item>
  <item name="LNBchiudiFiltro.text" html="true" placeholder="false">&lt;img src='./../images/filtro_close.gif' alt='' align=middle&gt;Blenden Sie die Filter aus</item>
  <item name="LNBchiudiFiltro.status" html="false" placeholder="false">Blenden Sie die Filter aus</item>
  <item name="LNBchiudiFiltro.Tooltip" html="false" placeholder="false">Blenden Sie die Filter aus</item>
  <item name="LBmostra_t.text" html="false" placeholder="false">Anzeigen:</item>
  <item name="RBLvisualizza.1" html="false" placeholder="false">Dateien der aktuellen Mappe</item>
  <item name="RBLvisualizza.0" html="false" placeholder="false">Die letzten eingegebenen</item>
  <item name="RBLvisualizza.-1" html="false" placeholder="false">Alle Dateien der Community</item>
  <item name="LBcategoria_t.text" html="false" placeholder="false">Datei-Kategorie:</item>
  <item name="DDLcategoria.-1" html="false" placeholder="false">Alle</item>
  <item name="DDLcategoria.0" html="false" placeholder="false">Nicht verfügbar</item>
  <item name="LBdescrizione_t.text" html="false" placeholder="false">Beschreibung:</item>
  <item name="CBXdescrizione.text" html="false" placeholder="false">Anzeigen</item>
  <item name="DGFileDisponibile.FLDS_Ordine.HeaderText" disambiguation="O=ordine (un solo carattere)" html="false" placeholder="false">R</item>
  <item name="DGFileDisponibile.FLDS_Nome.HeaderText" disambiguation="materiale=file" html="false" placeholder="false">Material</item>
  <item name="DGFileDisponibile.FLDS_dimensione.HeaderText" description="Dimens. = dimensione" html="false" placeholder="false">Grösse(KB)</item>
  <item name="DGFileDisponibile.FLDS_dataInserimento.HeaderText" html="false" placeholder="false">Upload-Datum</item>
  <item name="DGFileDisponibile.autore.HeaderText" description="Propr. = proprietario" html="false" placeholder="false">Inh.</item>
  <item name="LNBmanagement.text" html="false" placeholder="false">Verwaltung</item>
  <item name="LNBmanagement.status" html="false" placeholder="false">Verwaltung</item>
  <item name="LNBmanagement.ToolTip" html="false" placeholder="false">Verwaltung</item>
  <item name="LNBmanagementAvanzato.text" html="false" placeholder="false">Fortgeschrittene Verwaltung</item>
  <item name="LNBmanagementAvanzato.status" html="false" placeholder="false">Fortgeschrittene Verwaltung</item>
  <item name="LNBmanagementAvanzato.ToolTip" html="false" placeholder="false">Fortgeschrittene Verwaltung</item>
  <item name="LNBcreaDir.text" html="false" placeholder="false">Erstellen Sie eine Mappe</item>
  <item name="LNBcreaDir.status" html="false" placeholder="false">Erstellen Sie eine Mappe</item>
  <item name="LNBcreaDir.ToolTip" html="false" placeholder="false">Erstellen Sie eine Mappe</item>
  <item name="LNBupload.text" html="false" placeholder="false">Datei-Upload </item>
  <item name="LNBupload.status" html="false" placeholder="false">Datei-Upload </item>
  <item name="LNBupload.ToolTip" html="false" placeholder="false">Datei-Upload </item>
  <item name="LNBdettagliBack.text" html="false" placeholder="false">Kehren Sie zur Verwaltung zurück</item>
  <item name="LNBdettagliBack.status" html="false" placeholder="false">Kehren Sie zur Verwaltung zurück</item>
  <item name="LNBdettagliBack.ToolTip" html="false" placeholder="false">Kehren Sie zur Verwaltung zurück</item>
  <item name="LNBdettagliDownBack.text" html="false" placeholder="false">Kehren Sie zur Liste zurück</item>
  <item name="LNBdettagliDownBack.status" html="false" placeholder="false">Kehren Sie zur Liste zurück</item>
  <item name="LNBdettagliDownBack.ToolTip" html="false" placeholder="false">Kehren Sie zur Liste zurück</item>
  <item name="LNBsaveDir.text" html="false" placeholder="false">Sichern Sie die Daten</item>
  <item name="LNBsaveDir.status" html="false" placeholder="false">Sichern Sie die Daten</item>
  <item name="LNBsaveDir.ToolTip" html="false" placeholder="false">Sichern Sie die Daten</item>
  <item name="LNBcreaDirBack.text" html="false" placeholder="false">Kehren Sie zur Verwaltung zurück</item>
  <item name="LNBcreaDirBack.status" html="false" placeholder="false">Kehren Sie zur Verwaltung zurück</item>
  <item name="LNBcreaDirBack.ToolTip" html="false" placeholder="false">Kehren Sie zur Verwaltung zurück</item>
  <item name="LNBsaveFile.text" html="false" placeholder="false">Hinzufügen</item>
  <item name="LNBsaveFile.status" html="false" placeholder="false">Fügen Sie die Datei hinzu</item>
  <item name="LNBsaveFile.ToolTip" html="false" placeholder="false">Fügen Sie die Datei hinzu</item>
  <item name="LNBcreaFileBack.text" html="false" placeholder="false">Kehren Sie zur Verwaltung zurück</item>
  <item name="LNBcreaFileBack.status" html="false" placeholder="false">Kehren Sie zur Verwaltung zurück</item>
  <item name="LNBcreaFileBack.ToolTip" html="false" placeholder="false">Kehren Sie zur Verwaltung zurück</item>
  <item name="DGFileDisponibile.IMGDelete.status" html="false" placeholder="false">Löschen Sie die ausgewählte Datei.</item>
  <item name="DGFileDisponibile.IMGDelete.ToolTip" html="false" placeholder="false">Löschen</item>
  <item name="DGFileDisponibile.IMGDelete.ImageUrl" html="false" placeholder="false" hidden="true">./../images/elimina.gif</item>
  <item name="DGFileDisponibile.IMGDelete.ConfirmText" html="false" placeholder="false">Möchten Sie diese Datei wirklich löschen ? \r Die Datei wird aus dem Server endgültig entfernt !</item>
  <item name="DGFileDisponibile.IMGDelete.ImageUrl_disabled" html="false" placeholder="false" hidden="true">./../images/x_d.gif</item>
  <item name="DGFileDisponibile.IMGEdit.status" html="false" placeholder="false">Ändern Sie die Dateidetails.</item>
  <item name="DGFileDisponibile.IMGEdit.ToolTip" disambiguation="verbo" html="false" placeholder="false">Ändern</item>
  <item name="DGFileDisponibile.IMGEdit.ImageUrl" html="false" placeholder="false" hidden="true">./../images/m.gif</item>
  <item name="DGFileDisponibile.IMGDettagli.status" html="false" placeholder="false">Details der ausgewählten Datei.</item>
  <item name="DGFileDisponibile.IMGDettagli.ToolTip" html="false" placeholder="false">Details</item>
  <item name="DGFileDisponibile.IMGDettagli.ImageUrl" html="false" placeholder="false" hidden="true">./../images/proprieta.gif</item>
  <item name="DGFileDisponibile.IMGutente.status" html="false" placeholder="false">Änderung des Inhabers.</item>
  <item name="DGFileDisponibile.IMGutente.ToolTip" html="false" placeholder="false">Änderung des Inhabers</item>
  <item name="DGFileDisponibile.IMGutente.ImageUrl" html="false" placeholder="false" hidden="true">./../images/persona.gif</item>
  <item name="LBpercorso_t.text" disambiguation="percorso file" html="true" placeholder="false">&lt;b&gt;Pfad:&amp;nbsp;&lt;/b&gt;</item>
  <item name="File" html="false" placeholder="false">Datei</item>
  <item name="HYPdownload.text" html="false" placeholder="false">Download</item>
  <item name="HYPdownload.status" html="false" placeholder="false">Download</item>
  <item name="HYPdownload.Tooltip" html="false" placeholder="false">Download</item>
  <item name="LNBspostaIn.text" html="false" placeholder="false">Verschieben in..</item>
  <item name="LNBspostaIn.status" html="false" placeholder="false">In eine andere Mappe verschieben</item>
  <item name="LNBspostaIn.Tooltip" html="false" placeholder="false">In eine andere Mappe verschieben</item>
  <item name="LNBmostraNascondi.True.text" html="false" placeholder="false">Ausblenden</item>
  <item name="LNBmostraNascondi.True.status" html="false" placeholder="false">Blenden Sie die ausgewählte Datei aus.</item>
  <item name="LNBmostraNascondi.True.ToolTip" html="false" placeholder="false">Blenden Sie die ausgewählte Datei aus.</item>
  <item name="LNBmostraNascondi.False.text" html="false" placeholder="false">Anzeigen</item>
  <item name="LNBmostraNascondi.False.status" html="false" placeholder="false">Zeigen Sie die ausgewählte Datei an.</item>
  <item name="LNBmostraNascondi.False.ToolTip" html="false" placeholder="false">Zeigen Sie die ausgewählte Datei an.</item>
  <item name="SENZAproprietario" html="false" placeholder="false">Datei ohne Inhaber</item>
  <item name="NONvisibile" html="false" placeholder="false">Datei nicht sichtbar</item>
  <item name="LNBmodificaBack.text" html="false" placeholder="false">Kehren Sie zur Verwaltung zurück</item>
  <item name="LNBmodificaBack.status" html="false" placeholder="false">Kehren Sie zur Verwaltung zurück</item>
  <item name="LNBmodificaBack.Tooltip" html="false" placeholder="false">Kehren Sie zur Verwaltung zurück</item>
  <item name="LNBsave.text" html="false" placeholder="false">Sichern Sie die Einstellungen</item>
  <item name="LNBsave.status" html="false" placeholder="false">Sichern Sie die Einstellungen</item>
  <item name="LNBsave.Tooltip" html="false" placeholder="false">Sichern Sie die Einstellungen</item>
  <item name="inserimento.-12" html="false" placeholder="false">Der Verzeichnispfad ist zu lang, es ist nicht möglich, fortzufahren.</item>
  <item name="inserimento.-6" html="false" placeholder="false">Typologie der fehlenden Datei !</item>
  <item name="inserimento.-5" html="false" placeholder="false">Fehler beim Sichern der Daten !</item>
  <item name="inserimento.-4" html="false" placeholder="false">Datei nicht gefunden !</item>
  <item name="inserimento.-3" html="false" placeholder="false">Nicht alle Mussfelder sind vollständig !</item>
  <item name="inserimento.-2" html="false" placeholder="false">Die Kategorie der Datei ist nicht verfügbar, es ist nicht möglich, die Änderungen zu sichern !</item>
  <item name="inserimento.-1" html="false" placeholder="false">Fehler bei der Änderung der Daten, Vorgang nicht abgeschlossen!</item>
  <item name="inserimento.0" html="false" placeholder="false">Datei nicht erstellt, Fehler beim Upload !</item>
  <item name="inserimento.-7" html="false" placeholder="false">Die gewünschte Mappe wurde nicht erstellt !</item>
  <item name="inserimento.1" html="false" placeholder="false">Eingabe richtig durchgeführt.</item>
  <item name="inserimento.2" html="false" placeholder="false">Änderung richtig vorgenommen.</item>
  <item name="inserimento.4" html="false" placeholder="false">Die Mappe wurde richtig erstellt.</item>
  <item name="inserimento.5" html="false" placeholder="false">Die Datei wurde richtig erstellt; um den Upload einer neuen Datei durchzuführen, verwenden Sie den Link "Weiterer Upload". Um die Datei in andere Communities zu kopieren, klicken Sie auf "Kopieren in..".</item>
  <item name="inserimento.-8" html="false" placeholder="false">Die Datei ist bereits vorhanden !</item>
  <item name="inserimento.-9" html="false" placeholder="false">Fehler beim Datei-Upload !</item>
  <item name="inserimento.-10" html="false" placeholder="false">Die Mappe ist bereits vorhanden !</item>
  <item name="Spostamento.2" html="false" placeholder="false">Initialisierung vervollständigt</item>
  <item name="Spostamento.1" html="false" placeholder="false">Verschiebung erfolgreich durchgeführt !</item>
  <item name="Spostamento.0" html="false" placeholder="false">Fehler bei der Verschiebung !</item>
  <item name="Spostamento.-1" html="false" placeholder="false">Fehler, Vorgang nicht abgeschlossen !</item>
  <item name="Spostamento.-2" html="false" placeholder="false">Keine Zielmappe identifiziert !</item>
  <item name="Spostamento.-3" html="false" placeholder="false">Keine zu verschiebende Datei ausgewählt !</item>
  <item name="Spostamento.-4" html="false" placeholder="false">Die Zielmappe befindet sich in einem zu langen Pfad !</item>
  <item name="Spostamento.-5" html="false" placeholder="false">Zu verschiebende Datei nicht gefunden !</item>
  <item name="Spostamento.-6" html="false" placeholder="false">Verzeichnis nicht gefunden !</item>
  <item name="Spostamento.-7" html="false" placeholder="false">Element nicht gefunden !</item>
  <item name="Spostamento.-8" html="false" placeholder="false">Die Datei ist in der Zielmappe bereits vorhanden !</item>
  <item name="Spostamento.-9" html="false" placeholder="false">Die Mappe ist in der Zielmappe bereits vorhanden !</item>
  <item name="LNBaltroBack.text" html="false" placeholder="false">Kehren Sie zur Verwaltung zurück</item>
  <item name="LNBaltroBack.status" html="false" placeholder="false">Kehren Sie zur Verwaltung zurück</item>
  <item name="LNBaltroBack.Tooltip" html="false" placeholder="false">Kehren Sie zur Verwaltung zurück</item>
  <item name="LNBriprova.text" html="false" placeholder="false">Wieder versuchen</item>
  <item name="LNBriprova.status" html="false" placeholder="false">Wieder versuchen</item>
  <item name="LNBriprova.Tooltip" html="false" placeholder="false">Wieder versuchen</item>
  <item name="LNBmultiplo.text" html="false" placeholder="false">Kopie in..</item>
  <item name="LNBmultiplo.status" html="false" placeholder="false">Kopie in..</item>
  <item name="LNBmultiplo.Tooltip" html="false" placeholder="false">Kopie in..</item>
  <item name="LNBaggiungiAltro.text" html="false" placeholder="false">Anderer Upload</item>
  <item name="LNBaggiungiAltro.status" html="false" placeholder="false">Anderer Upload</item>
  <item name="LNBaggiungiAltro.Tooltip" html="false" placeholder="false">Anderer Upload</item>
  <item name="LNBaggiungiAltro.dir.text" html="false" placeholder="false">Erstellen Sie ein anderes Verzeichnis </item>
  <item name="LNBaggiungiAltro.dir.status" html="false" placeholder="false">Erstellen Sie ein anderes Verzeichnis </item>
  <item name="LNBaggiungiAltro.dir.Tooltip" html="false" placeholder="false">Erstellen Sie ein anderes Verzeichnis </item>
  <item name="LNBannullaMultiplo.text" html="false" placeholder="false">Kehren Sie zur Verwaltung zurück</item>
  <item name="LNBannullaMultiplo.status" html="false" placeholder="false">Kehren Sie zur Verwaltung zurück</item>
  <item name="LNBannullaMultiplo.Tooltip" html="false" placeholder="false">Kehren Sie zur Verwaltung zurück</item>
  <item name="LNBassocia.text" html="false" placeholder="false">Kopie in die ausgewählten</item>
  <item name="LNBassocia.status" html="false" placeholder="false">Kopie in die ausgewählten</item>
  <item name="LNBassocia.Tooltip" html="false" placeholder="false">Kopie in die ausgewählten</item>
  <item name="multiplo.-11" html="false" placeholder="false">Keine Community/Zielmappe ausgewählt !</item>
  <item name="multiplo.-10" html="false" placeholder="false">Die Mappe ist bereits vorhanden !</item>
  <item name="multiplo.-8" html="false" placeholder="false">Die Datei ist bereits vorhanden !</item>
  <item name="multiplo.-7" html="false" placeholder="false">Mappe nicht gefunden !</item>
  <item name="multiplo.-5" html="false" placeholder="false">Fehler beim Sichern der Daten !</item>
  <item name="multiplo.-4" html="false" placeholder="false">Datei nicht gefunden !</item>
  <item name="multiplo.1" html="false" placeholder="false">Kopie der Datei in andere Communities erfolgreich vollständig ausgeführt !</item>
  <item name="LNBmodificaDir.text" html="false" placeholder="false">Ändern Sie das Verzeichnis</item>
  <item name="LNBmodificaDir.status" html="false" placeholder="false">Ändern Sie das Verzeichnis</item>
  <item name="LNBmodificaDir.Tooltip" html="false" placeholder="false">Ändern Sie das Verzeichnis</item>
  <item name="LNBcancellaContenuto.text" html="false" placeholder="false">Löschen Sie Dateien</item>
  <item name="LNBcancellaContenuto.status" html="false" placeholder="false">Löschen Sie Dateien</item>
  <item name="LNBcancellaContenuto.Tooltip" html="false" placeholder="false">Löschen Sie Dateien</item>
  <item name="LNBcancellaContenuto.ConfirmText" html="false" placeholder="false">Möchten Sie alle Dateien der aktuellen Mappe wirklich löschen?</item>
  <item name="LNBbackSposta.text" html="false" placeholder="false">Kehren Sie zur Verwaltung zurück</item>
  <item name="LNBbackSposta.status" html="false" placeholder="false">Kehren Sie zur Verwaltung zurück</item>
  <item name="LNBbackSposta.Tooltip" html="false" placeholder="false">Kehren Sie zur Verwaltung zurück</item>
  <item name="LNBspostaFile.text" html="false" placeholder="false">Verschieben</item>
  <item name="LNBspostaFile.status" html="false" placeholder="false">Verschieben</item>
  <item name="LNBspostaFile.Tooltip" html="false" placeholder="false">Verschieben</item>
  <item name="LNBspostaEsovrascrivi.text" html="false" placeholder="false">Verschieben und ersetzen</item>
  <item name="LNBspostaEsovrascrivi.status" html="false" placeholder="false">Verschieben und ersetzen, falls vorhanden</item>
  <item name="LNBspostaEsovrascrivi.Tooltip" html="false" placeholder="false">Verschieben und ersetzen, falls vorhanden</item>
  <item name="LNBspostaEsovrascrivi.ConfirmText" html="false" placeholder="false">Verschieben Sie das Material/die Materialien und ersetzen Sie es/sie, falls es/sie bereits vorhanden ist/sind ?</item>
  <item name="downloadTxt" html="false" placeholder="false">Heruntergeladen: </item>
  <item name="cartellaBase" html="false" placeholder="false">Basismappe</item>
  <item name="RedirectMessage" html="false" placeholder="false">Die ausgewählte Seite ist nicht mehr vorhanden (Ihr Bookmark/Ihre Favorite ist fehlerhaft oder der Proxy-Server hat die Seite nicht richtig aktualisiert).\rKlicken sie auf ok und Sie werden zur richtigen Seite erneut weitergeleitet !</item>
  <item name="LBdescrizioneFile" html="false" placeholder="false">Beschreibung:</item>
  <item name="LNBmostraFile.text" html="false" placeholder="false">Zeigen Sie alle an</item>
  <item name="LNBmostraFile.status" html="false" placeholder="false">Alle Dateien sichtbar einstellen</item>
  <item name="LNBmostraFile.Tooltip" html="false" placeholder="false">Alle Dateien sichtbar einstellen</item>
  <item name="LNBnascondiFile.text" html="false" placeholder="false">Blenden Sie alle aus</item>
  <item name="LNBnascondiFile.status" html="false" placeholder="false">Blenden Sie alle Dateien aus</item>
  <item name="LNBnascondiFile.Tooltip" html="false" placeholder="false">Blenden Sie alle Dateien aus</item>
  <item name="HYPcontenutoAttivo.scorm.text" html="false" placeholder="false">(Play Paket)</item>
  <item name="HYPcontenutoAttivo.scorm.status" html="false" placeholder="false">(Play Paket)</item>
  <item name="HYPcontenutoAttivo.scorm.Tooltip" html="false" placeholder="false">(Play Paket)</item>
  <item name="IMBcontenutoAttivo.scorm.status" html="false" placeholder="false">(Play Paket)</item>
  <item name="IMBcontenutoAttivo.scorm.Tooltip" html="false" placeholder="false">(Play Paket)</item>
  <item name="HYPcontenutoAttivo.videocast.text" html="false" placeholder="false">(Video wiedergeben)</item>
  <item name="HYPcontenutoAttivo.videocast.status" html="false" placeholder="false">(Video wiedergeben)</item>
  <item name="HYPcontenutoAttivo.videocast.Tooltip" html="false" placeholder="false">(Video wiedergeben)</item>
  <item name="IMBcontenutoAttivo.videocast.status" html="false" placeholder="false">(Video wiedergeben)</item>
  <item name="IMBcontenutoAttivo.videocast.Tooltip" html="false" placeholder="false">(Video wiedergeben)</item>
  <item name="LNBstatistics.text" html="false" placeholder="false" hidden="true">&lt;img src="{0}" ToolTip="{1}"&gt;</item>
  <item name="HYPstatistics.status" html="false" placeholder="false">Datei-Statistiken</item>
  <item name="HYPstatistics.ToolTip" html="false" placeholder="false">Datei-Statistiken</item>
  <item name="oRootNodeCartelle.Text" html="false" placeholder="false">Basismappe</item>
</Resource>