<?xml version="1.0" encoding="utf-8" ?>
<Resource xmlns="urn:ComolTranslation">
	<item name="LBtitolo.text">Management tipi comunità</item>
	<item name="LBNopermessi.text">Non dispone dei permessi necessari per accedere a questa pagina.</item>
	<item name="LogoutMessage">Spiacenti, la sessione è scaduta.Dovrà effettuare nuovamente l'accesso al sistema.</item>
	<item name="DGtipoComunita.page" placeholder="true" mustcontains="#%%#">Pagina &lt;#%%#&gt;</item>
	<item name="DGtipoComunita.ordinamento.0.status" placeholder="true" mustcontains="#%%#">Ordinamento crescente per &lt;#%%#&gt;</item>
	<item name="DGtipoComunita.ordinamento.1.status" placeholder="true" mustcontains="#%%#">Ordinamento decrescente per &lt;#%%#&gt;</item>
	<item name="DGtipoComunita.ordinamento.2.status" placeholder="true" mustcontains="#%%#">Ordina per &lt;#%%#&gt;</item>
	<item name="DGtipoComunita.TPCM_descrizione.HeaderText" disambiguation="singolare">Tipo comunità</item>
	<item name="DGtipoComunita.Comunita.HeaderText">Comunità Associate</item>
	<item name="titolo.inserimento">Management tipi comunità: nuova tipologia</item>
	<item name="titolo.modifica">Management tipi comunità: modifica</item>
	<item name="LNBinserisci.text">Crea nuovo</item>
	<item name="LNBinserisci.status">Crea nuovo tipo di comunità</item>
	<item name="LNBinserisci.ToolTip">Crea nuovo tipo di comunità</item>
	<item name="LNBindietro.text">Torna all'elenco</item>
	<item name="LNBindietro.status">Torna all'elenco</item>
	<item name="LNBindietro.ToolTip">Torna all'elenco</item>
	<item name="LNBaddRuolo.text">Aggiungi ruolo</item>
	<item name="LNBaddRuolo.status">Aggiungi ruolo</item>
	<item name="LNBaddRuolo.ToolTip">Aggiungi ruolo</item>
	<item name="LNBdefault.text">Impostazioni default</item>
	<item name="LNBdefault.status">Impostazioni di default</item>
	<item name="LNBdefault.ToolTip">Impostazioni di default</item>
	<item name="LNBtipocomunitaForAll.text">Replica su tutte</item>
	<item name="LNBtipocomunitaForAll.status">Salva i valori e li replica sulle altre organizzazioni</item>
	<item name="LNBtipocomunitaForAll.ToolTip">Replica valori sulle altre organizzazioni</item>
	<item name="LNBsalvaDati.text">Salva</item>
	<item name="LNBsalvaDati.status">Salva</item>
	<item name="LNBsalvaDati.ToolTip">Salva</item>
	<item name="TABcategoriaFile.Text">Categorie file</item>
	<item name="TABcategoriaFile.ToolTip">Categorie file</item>
	<item name="TABmodelli.Text" disambiguation="modello=modello di comunità">Modelli</item>
	<item name="TABmodelli.ToolTip">Modelli stile</item>
	<item name="TABpermessi.Text">Permessi</item>
	<item name="TABpermessi.ToolTip">Permessi relativi ai servizi associati</item>
	<item name="TABservizio.Text">Servizi</item>
	<item name="TABservizio.ToolTip">Servizi associati</item>
	<item name="TABtipologia.Text">Dati Tipologia</item>
	<item name="TABtipologia.ToolTip">Dati Tipologia</item>
	<item name="TABtipoRuolo.Text">Ruoli associati</item>
	<item name="TABtipoRuolo.ToolTip">Ruoli associati</item>
	<item name="TABruoliProfilo.Text">Ruoli Profilo</item>
	<item name="TABruoliProfilo.ToolTip">Ruoli SEMPRE disponibili nei profili personali</item>
	<item name="Inserimento.0">Errore nell'esecuzione dell'operazione</item>
	<item name="Inserimento.1">Tipo comunità creato correttamente</item>
	<item name="Inserimento.2">Modifica effettuata</item>
	<item name="Inserimento.3">Servizi associati in modo corretto</item>
	<item name="Inserimento.4">Impostazioni permessi registrate correttamente</item>
	<item name="Inserimento.5">Servizi attivati di defualt registrati correttamente</item>
	<item name="Inserimento.6">Ruoli associati in modo corretto: verificare definizione permessi</item>
	<item name="Inserimento.-1">Manca la descrizione del tipo di comunità, impossibile continuare !</item>
	<item name="Inserimento.-2">Modifica NON effettuata</item>
	<item name="Inserimento.-3">Il nuovo tipo di comunità NON è stato creato correttamente</item>
	<item name="Inserimento.-4">ATTENZIONE: selezionare almeno una categoria di file</item>
	<item name="Inserimento.-5">ATTENZIONE: selezionare almeno un modello</item>
	<item name="Inserimento.-6">ATTENZIONE: selezionare almeno un servizio</item>
	<item name="Inserimento.-7">Errore nella registrazione delle impostazioni relative ai servizi.</item>
	<item name="Inserimento.-8">ATTENZIONE: specificare almeno un ruolo !</item>
	<item name="Inserimento.-9">ATTENZIONE: nessun servizio individuato !</item>
	<item name="Inserimento.-10">ATTENZIONE: permessi associati in modo parziale !</item>
	<item name="Inserimento.-11">ATTENZIONE: nessun file immagine specificato !</item>
	<item name="Inserimento.-12">ATTENZIONE: nessun ruolo obbligatorio da utilizzare nei profili è stato definito !</item>
	<item name="LBnorecord.text">Nessun tipo di comunità trovato nel sistema !</item>
	<item name="Si">Si</item>
	<item name="No">No</item>
</Resource>