<?xml version="1.0" encoding="utf-8"?>
<!-- eng -->
<Resource xmlns:xsi="http://www.w3.org/2001/XMLSchema-instance" xmlns:xsd="http://www.w3.org/2001/XMLSchema" xmlns="urn:ComolTranslation">
  <item name="LBTitolo.text" html="false" placeholder="false">Wiki</item>
  <item name="LBL_NoPermessi.text" html="false" placeholder="false">You do not have permission to access this service</item>
  <item name="LBL_NoWiki.text" html="false" placeholder="false">The Wiki for this community has not been created, yet.per questa comunità non è ancora stata creata</item>
  <item name="LBL_Nav_NoSezione.text" html="false" placeholder="false">No section found</item>
  <item name="LBL_Con_SezioneNO.text" html="false" placeholder="false">There are no sections for the related Wiki</item>
  <item name="LBL_NoTopic_t.text" html="false" placeholder="false">No Topic for selected section.</item>
  <item name="LBL_NoTopicAdd_t.text" html="false" placeholder="false">Press "Add Topic" in the upper right to add a new Topic.</item>
  <item name="LBL_Back_t.text" html="false" placeholder="false">Back to top</item>
  <item name="Lbl_NASezione_Nome_t.text" html="false" placeholder="false">Section name:</item>
  <item name="Lbl_NASezione_Descrizione_t.text" html="false" placeholder="false">Description:</item>
  <item name="LBL_ModTopic_Titolo_t.text" html="false" placeholder="false">Topic title:</item>
  <item name="LBL_ElencoSezioneDescrizione_t.text" html="false" placeholder="false">Topic text:</item>
  <item name="LBL_ElencoSezionePersona_t.text" html="false" placeholder="false">Written by:</item>
  <item name="CBX_NASezione_IsPubblica_t.text" disambiguation="aggettivo" html="false" placeholder="false">Public</item>
  <item name="CBX_NASezione_IsDefault.text" html="false" placeholder="false">Main</item>
  <item name="LBL_NoWikiADD.text" html="false" placeholder="false">To create a Wiki in this communit, entrer a name and then click "Save".</item>
  <item name="LBL_WikiAdd_Nome_t.text" html="false" placeholder="false">New Wiki name:</item>
  <item name="Btn_AnnWiki.text" html="false" placeholder="false">Cancel</item>
  <item name="Btn_AnnWiki.ToolTip" html="false" placeholder="false">Cancel insertion</item>
  <item name="Btn_AnnWiki.status" html="false" placeholder="false">Cancel insertion</item>
  <item name="BTN_AddWiki.text" html="false" placeholder="false">Save</item>
  <item name="BTN_AddWiki.ToolTip" html="false" placeholder="false">Adds new Wiki</item>
  <item name="BTN_AddWiki.status" html="false" placeholder="false">Adds new Wiki</item>
  <item name="LBL_Navigatore_t.text" html="false" placeholder="false">Present sections list</item>
  <item name="LBL_LinkTopic_t.text" html="false" placeholder="false">Topic index</item>
  <item name="BTN_AddSezione.text" html="false" placeholder="false">Add section</item>
  <item name="BTN_AddSezione.ToolTip" html="false" placeholder="false">Add a new Section to current Wiki</item>
  <item name="BTN_AddSezione.status" html="false" placeholder="false">Add a new Section to current Wiki</item>
  <item name="BTN_ModSezione.text" html="false" placeholder="false">Modify Section</item>
  <item name="BTN_ModSezione.ToolTip" html="false" placeholder="false">Modify current Section</item>
  <item name="BTN_ModSezione.status" html="false" placeholder="false">Modify current Section</item>
  <item name="BTN_Addtopic.text" html="false" placeholder="false">Add Topic</item>
  <item name="BTN_Addtopic.ToolTip" html="false" placeholder="false">Add a topic to current section</item>
  <item name="BTN_Addtopic.status" html="false" placeholder="false">Add a topic to current section</item>
  <item name="BTN_ModWiki.text" html="false" placeholder="false">Modify Wiki</item>
  <item name="BTN_ModWiki.ToolTip" html="false" placeholder="false">Modify current Wiki </item>
  <item name="BTN_ModWiki.status" html="false" placeholder="false">Modify current Wiki </item>
  <item name="BTNSaveQuit.text" html="false" placeholder="false">Save and exit</item>
  <item name="BTNSaveQuit.ToolTip" html="false" placeholder="false">Save current changes</item>
  <item name="BTNSaveQuit.status" html="false" placeholder="false">Save current changes and back to the Topics list in the current section</item>
  <item name="BTNSaveContinua.text" html="false" placeholder="false">Save and continue</item>
  <item name="BTNSaveContinua.ToolTip" html="false" placeholder="false">Save current changes and continue with modification/insertion.</item>
  <item name="BTNSaveContinua.status" html="false" placeholder="false">Save current changes and continue with modification/insertion.</item>
  <item name="BTNRipristina.text" html="false" placeholder="false">Restore</item>
  <item name="BTNRipristina.ToolTip" html="false" placeholder="false">Restore Topic</item>
  <item name="BTNRipristina.status" html="false" placeholder="false">Restore current Topic</item>
  <item name="BTNRipristina.ConfirmText" html="false" placeholder="false">Are you sure you want to restore the Topic?</item>
  <item name="BTNEdit.text" disambiguation="verbo" html="false" placeholder="false">Modify</item>
  <item name="BTNEdit.ToolTip" html="false" placeholder="false">Modify Topic</item>
  <item name="BTNEdit.status" html="false" placeholder="false">Modify Topic</item>
  <item name="BTNDel.text" html="false" placeholder="false">Delete</item>
  <item name="BTNDel.ToolTip" html="false" placeholder="false">Delete Topic</item>
  <item name="BTNDel.status" html="false" placeholder="false">Delete topic</item>
  <item name="BTNDel.ConfirmText" html="false" placeholder="false">Are you sure you want to delete the Topic?</item>
  <item name="BTNCrono.text" html="false" placeholder="false">History</item>
  <item name="BTNCrono.ToolTip" html="false" placeholder="false">Show history</item>
  <item name="BTNCrono.status" html="false" placeholder="false">Display current topic chronology</item>
  <item name="InfoTopic" html="false" placeholder="true" mustcontains="#%creata%#|#%modificata%#|#%autore%#">Created on #%creata%# and modified on #%modificata%# by #%autore%#</item>
  <item name="DLTopics.Modifica" html="false" placeholder="false">Modify^</item>
  <item name="DLTopics.Cronologia" html="false" placeholder="false">History^</item>
  <item name="DLTopics.Ripristina" html="false" placeholder="false">Restore^</item>
  <item name="BTNDel.text.Ripristina" html="false" placeholder="false">Restore</item>
  <item name="BTNDel.ToolTip.Ripristina" html="false" placeholder="false">Restore</item>
  <item name="BTNDel.ConfirmText.Ripristina" html="false" placeholder="false">Are you sure you want to restore Topic?</item>
  <item name="BTNDel.status.Ripristina" html="false" placeholder="false">Recover Topic from deletion</item>
  <item name="BTNDel.text.Elimina" html="false" placeholder="false">Delete</item>
  <item name="BTNDel.ToolTip.Elimina" html="false" placeholder="false">Delete</item>
  <item name="BTNDel.ConfirmText.Elimina" html="false" placeholder="false">Are you sure you want to delete the Topic?</item>
  <item name="BTNDel.status.Elimina" html="false" placeholder="false">Delete Topic</item>
  <item name="BTN_RecSezione.text" html="false" placeholder="false">Recover</item>
  <item name="BTN_RecSezione.ToolTip" html="false" placeholder="false">Recover Sections</item>
  <item name="BTN_RecSezione.ConfirmText" html="false" placeholder="false">Recover section?</item>
  <item name="BTN_RecSezione.status" html="false" placeholder="false">Recover current section.</item>
  <item name="BTN_DelSezione.text" html="false" placeholder="false">Delete section</item>
  <item name="BTN_DelSezione.ToolTip" html="false" placeholder="false">Delete section</item>
  <item name="BTN_DelSezione.ConfirmText" html="false" placeholder="false">Delete section?</item>
  <item name="BTN_DelSezione.status" html="false" placeholder="false">Delete current section</item>
  <item name="LnkSezione.IsDeleted" html="false" placeholder="true" mustcontains="#%%#">[DELETED: #%%#]</item>
  <item name="BTN_Home.text" html="false" placeholder="false">Wiki home</item>
  <item name="BTN_Import.text" html="false" placeholder="false">Import Topic</item>
  <item name="BTN_importa.text" html="false" placeholder="false">Import</item>
  <item name="BTN_deselTutti.text" html="false" placeholder="false">Deselect all</item>
  <item name="BTN_selTutti.text" html="false" placeholder="false">Select all</item>
  <item name="LBL_PassoUno.text" html="false" placeholder="false">Step 1: Select the community from which import the wanted topics</item>
  <item name="LBL_PassoDue.text" html="false" placeholder="false">Step 2: Select Topics you want to import and then press "Import"</item>
  <item name="LBL_ricerca.text" html="false" placeholder="false">Search:</item>
  <item name="BTN_search.text" html="false" placeholder="false">Search</item>
  <item name="BTN_EditView.text" html="false" placeholder="false">Modify^</item>
  <item name="BTNRip.text" html="false" placeholder="false">Restore</item>
  <item name="BTNRip.ToolTip" html="false" placeholder="false">Restore Topic</item>
  <item name="BTNRip.status" html="false" placeholder="false">Restore Topic</item>
  <item name="LBL_intVoce1.text" disambiguation="voce=voce/elemento del diario delle lezioni/quarderno attività" html="false" placeholder="false">Item</item>
  <item name="LBL_intSezione1.text" html="false" placeholder="false">Section</item>
  <item name="LBL_intVoce.text" disambiguation="voce=voce/elemento del diario delle lezioni/quarderno attività" html="false" placeholder="false">Item</item>
  <item name="LBL_intSezione.text" html="false" placeholder="false">Section</item>
  <item name="LBL_intComunita.text" disambiguation="singolare" html="false" placeholder="false">Community</item>
  <item name="CBX_SezVisEliminate.text" html="false" placeholder="false">View deleted Sections and Topics </item>
  <item name="CBX_Topic_IsPubblico.text" html="false" placeholder="false">Topic is public(visible in the whole site)</item>
  <item name="BTN_Torna.text" html="false" placeholder="false">Back to section</item>
  <item name="BTN_Sezione_Salva.text" html="false" placeholder="false">Save</item>
  <item name="BTN_Sezione_Annulla.text" html="false" placeholder="false">Cancel</item>
  <item name="LBL_proce1.text" html="false" placeholder="false">of current community</item>
  <item name="LBL_proce.text" html="false" placeholder="false">Guided Topic importation procedure in the current section</item>
</Resource>